{
    "variant_categories": [
        {
            "id": "d037ccf9-1384-4338-8192-e673c446e50e",
            "master_variant_category_id": "b243f255-2efb-4816-b2ee-4cd4aa712c60",
            "restaurant_id": "a548ac8a-8d08-4fe4-b2ed-7c15e93c7069",
            "name": "Pilihan topping",
            "internal_name": "",
            "rules": {
                "selection": {
                    "type": "SELECT_MANY",
                    "required": false,
                    "min_quantity": 0,
                    "max_quantity": null
                }
            },
            "variants": [
                {
                    "id": "ddb6e232-4ab8-4a3f-bd65-4aa5a5647fcc",
                    "variant_category_id": "d037ccf9-1384-4338-8192-e673c446e50e",
                    "master_variant_id": "0ec9d296-3df0-42a4-9c7f-054c3d17840b",
                    "restaurant_id": "a548ac8a-8d08-4fe4-b2ed-7c15e93c7069",
                    "name": "Keju",
                    "active": true,
                    "price": 4000,
                    "weight": 1,
                    "in_stock": true
                },
                {
                    "id": "0eb61df6-b647-4873-83c7-478a10875cc4",
                    "variant_category_id": "d037ccf9-1384-4338-8192-e673c446e50e",
                    "master_variant_id": "a125fd89-8bbf-494f-8515-e63b31496bb9",
                    "restaurant_id": "a548ac8a-8d08-4fe4-b2ed-7c15e93c7069",
                    "name": "Telur",
                    "active": true,
                    "price": 4000,
                    "weight": 2,
                    "in_stock": true
                },
                {
                    "id": "ebd7188c-ea10-459b-887e-f4b077396b34",
                    "variant_category_id": "d037ccf9-1384-4338-8192-e673c446e50e",
                    "master_variant_id": "d776e7f2-715d-46f3-a6a4-ac0f959723c2",
                    "restaurant_id": "a548ac8a-8d08-4fe4-b2ed-7c15e93c7069",
                    "name": "mazorella",
                    "active": true,
                    "price": 8000,
                    "weight": 3,
                    "in_stock": true
                },
                {
                    "id": "13fbbebf-9bc3-4c8d-bf6b-c2eca82b6062",
                    "variant_category_id": "d037ccf9-1384-4338-8192-e673c446e50e",
                    "master_variant_id": "1553fe94-9d90-4efd-9b2f-785ab5ccf3c6",
                    "restaurant_id": "a548ac8a-8d08-4fe4-b2ed-7c15e93c7069",
                    "name": "dobel keju mozarella",
                    "active": true,
                    "price": 15000,
                    "weight": 4,
                    "in_stock": true
                }
            ]
        }
    ]
}